msfunds/FundsData.py
msfunds/FundsScreener.py
msfunds/__init__.py
msfunds/Utils/Constants.py
msfunds/Utils/Fields.json
msfunds/Utils/Keys.json
msfunds/Utils/Sites.json
msfunds/Utils/URLs.json
msfunds/Utils/__init__.py
msfunds-1.1.dist-info/METADATA
msfunds-1.1.dist-info/WHEEL
msfunds-1.1.dist-info/top_level.txt
msfunds-1.1.dist-info/RECORD
