Metadata-Version: 2.1
Name: msfunds
Version: 1.1
Summary: Fetches Funds data from Morningstar.
Home-page: https://github.com/nndjoli/morningstar-funds-data-fetcher
Author: nndjoli
License: UNKNOWN
Platform: UNKNOWN
Classifier: Programming Language :: Python :: 3
Classifier: License :: OSI Approved :: MIT License
Classifier: Operating System :: OS Independent
Requires-Python: >=3.7
Requires-Dist: pandas
Requires-Dist: ua-generator
Requires-Dist: httpx
Requires-Dist: beautifulsoup4
Requires-Dist: nest-asyncio
Requires-Dist: importlib-resources ; python_version < "3.9"
